README.md
setup.py
logxs/__init__.py
logxs/__version__.py
logxs/logxs.py
logxs/meta.py
logxs.egg-info/PKG-INFO
logxs.egg-info/SOURCES.txt
logxs.egg-info/dependency_links.txt
logxs.egg-info/requires.txt
logxs.egg-info/top_level.txt